{
  "sections": {
    "main": {
      "type": "main-product",
      "blocks": {
        "vendor": {
          "type": "vendor",
          "settings": {
          }
        },
        "title": {
          "type": "title",
          "settings": {
          }
        },
        "price": {
          "type": "price",
          "settings": {
            "show_tax_and_shipping": false,
            "enable_product_reviews_by_price": false
          }
        },
        "2aaa1eab-6177-4c92-81be-176f8d7827c7": {
          "type": "shopify:\/\/apps\/judge-me-reviews\/blocks\/preview_badge\/61ccd3b1-a9f2-4160-9fe9-4fec8413e5d8",
          "settings": {
          }
        },
        "divider": {
          "type": "divider",
          "settings": {
            "show_in_quickbuy": false
          }
        },
        "41d6d1f0-1de6-4b1f-a560-895f740d9dcf": {
          "type": "sku",
          "settings": {
          }
        },
        "variant-picker": {
          "type": "variant-picker",
          "settings": {
            "show_single": false,
            "select_first_variant": true,
            "selector_style": "listed",
            "enable_dynamic_availability": true,
            "enable_size_chart": false,
            "size_chart_variant": "Size",
            "size_chart_page": ""
          }
        },
        "1d263577-6d2a-4030-bcfe-899e0c4b345e": {
          "type": "countdown",
          "settings": {
            "heading": "Get Free Awning",
            "end_date": "2024-06-11",
            "end_time": "",
            "end_text": "",
            "hide_on_end": false,
            "box_color": "#ffffff",
            "text_color": "#ff6100",
            "number_font": "base",
            "divider_type": "colon",
            "show_timer_labels": false,
            "show_in_quickbuy": false
          }
        },
        "buy-buttons": {
          "type": "buy-buttons",
          "settings": {
            "show_quantity_selector": true,
            "enable_payment_button": true,
            "show_backorder_text": false,
            "show_pickup_availability": true,
            "show_gift_card_recipient": false
          }
        },
        "description": {
          "type": "description",
          "disabled": true,
          "settings": {
            "show_in_tab": false,
            "open_tab": false,
            "icon": "",
            "show_in_quickbuy": false
          }
        },
        "144abbaf-b8f9-49b2-a699-0bb45081e4e1": {
          "type": "shopify:\/\/apps\/seoant-trust-badges\/blocks\/star_rating\/f42f2346-5d14-4b41-a8b9-4b6ee352262e",
          "settings": {
            "badge_id": ""
          }
        },
        "selleasy_lb_upsell_fbt_block_HKybby": {
          "type": "shopify:\/\/apps\/selleasy\/blocks\/lb-upsell-fbt-block\/790c1a03-a71f-4bc1-9869-00dad526d3c2",
          "settings": {
          }
        }
      },
      "block_order": [
        "vendor",
        "title",
        "price",
        "2aaa1eab-6177-4c92-81be-176f8d7827c7",
        "divider",
        "41d6d1f0-1de6-4b1f-a560-895f740d9dcf",
        "variant-picker",
        "1d263577-6d2a-4030-bcfe-899e0c4b345e",
        "buy-buttons",
        "description",
        "144abbaf-b8f9-49b2-a699-0bb45081e4e1",
        "selleasy_lb_upsell_fbt_block_HKybby"
      ],
      "settings": {
        "show_breadcrumbs": true,
        "show_location_underneath": false,
        "inventory_transfers_enable": true,
        "enable_sticky_columns": false,
        "gallery_size": "medium",
        "gallery_layout": "carousel-under",
        "enable_zoom": true,
        "show_alt_text": false,
        "alt_text_icon": "",
        "enable_video_autoplay": false,
        "enable_video_looping": false,
        "enable_media_grouping": false,
        "media_grouping_option": "Color,Colour,Couleur,Farbe"
      }
    },
    "2ca79a2a-7dff-41ad-8c5f-cb2bb7070dc4": {
      "type": "collapsible-tabs",
      "blocks": {
        "template--16416158613670__2ca79a2a-7dff-41ad-8c5f-cb2bb7070dc4-question-1": {
          "type": "question",
          "settings": {
            "title": "DESCRIPTION",
            "answer": "<ul><li>Ascendll™ aluminum shell tents are a popular choice due to their ease of use. This flap tent can be set up in just 10 seconds, making it one of the fastest tents to deploy and break down. The tent features several upgrades that make it stand out, including a thicker rubber seal that keeps it clean and dry, and a carpet that helps minimize moisture.<\/li><li>The Ascendll™ shell has a sleek aerodynamic design, adding only 8 inches of extra height and weighing only 136 lbs, making it lightweight and fuel-efficient. It also doubles as a roof rack, allowing you to mount lights, an awning, tools, or carry your sports equipment.<\/li><li>The tent interior has been stretched to 35'' \/ 6'' to allow taller campers to sit comfortably, and the interior height now has enough room to store ladders and bedding. The tent features an organizer bag with multiple pockets for entertainment.<\/li><li>The sleep experience in the Ascendll™ tent is exceptional. The 2-inch high-density foam padding provides extra cushioning and comes with a removable waterproof mattress cover. The canopy features light-suppressing technology that completely blocks any external light when fully closed, allowing you to sleep undisturbed.<\/li><li>The tent also comes with several subtle upgrades, including a larger wraparound awning and huge side windows that provide stunning views.<\/li><li>Overall, Ascendll™ aluminum shell tents provide an excellent camping experience, with added comfort and convenience.<\/li><\/ul>"
          }
        },
        "template--16416158613670__2ca79a2a-7dff-41ad-8c5f-cb2bb7070dc4-question-2": {
          "type": "question",
          "settings": {
            "title": "SPECIFICATIONS",
            "answer": "<ul><li><strong>Sleeping Capacity: <\/strong>2-3 People<\/li><li><strong>Closed Size L\/W\/H: <\/strong>83x52x6 Inch<\/li><li><strong>External Unfolded Size L\/W\/H: <\/strong>83x55x59 Inch<\/li><li><strong>Internal Unfolded Size L\/W\/H: <\/strong>79.5x49x57 Inch<\/li><li><strong>Mattress Size:  <\/strong>1 qty, Hight-D Memory Foam, 82x51x2 Inch<\/li><li><strong>Weight:<\/strong> 160 Lbs<\/li><li><strong>Weight Capacity<\/strong>: 1100 Lbs<\/li><li>Mounting T-Channel Rails: 26 Inch apart<\/li><li>Recommended Mounting Width: 26~32 Inch<\/li><\/ul><p><\/p><ul><li><strong>Shell Material: <\/strong>6-Seris  Aluminum with Jet-Black Powder Coating<\/li><li><strong>Tent Body Material:<\/strong> 600D Oxford\/Cotton Rip-Stop 280 GSM, Waterproof Level &gt;3000MM, UV50+, Mold-inhibiting fabric<\/li><li><strong>Rainfly<\/strong> <strong>Material: <\/strong>420D Oxford\/Cotton Rip-Stop 210 GSM, Waterproof Level &gt;3000MM, UV50+, Mold-inhibiting fabric<\/li><li><strong>Floor Material: <\/strong>Heavy-duty 1‘’ Aluminum Honeycomb Panel<\/li><li><strong>Doors & Window Material:<\/strong> 600D Poly-Oxford with 280GSM\/120g Poly-fil mesh<\/li><li><strong>Gas Struts:<\/strong> 2 qty, Rating 400N each<\/li><li><strong>Zippers: <\/strong>Heavy-duty SBS (contains air tight function)<\/li><li><strong>Ladder: <\/strong>Telescoping 7.6 ft tall((included))<\/li><li>2 qty, 2-pocket storage Bag made of 600D Oxford fabric<\/li><\/ul>"
          }
        },
        "29d84539-711c-42d9-9d3d-77976e8ad492": {
          "type": "question",
          "settings": {
            "title": "SHIPPING & RETURNS",
            "answer": "<h4><strong>LTL-Truck Shipping<\/strong><\/h4><p><strong>Delivery Countries: <\/strong>USA (Excluding outlying islands)<\/p><p><strong>Transit Time: <\/strong>7-15 business days<\/p><p>________________________________<\/p><p><strong>Transportation Costs: <\/strong>FREE<\/p><p><strong>Delivery Countries: <\/strong>Canada <\/p><p><strong>Transit Time: <\/strong>10-15 business days<\/p><p><strong>Transportation Costs:  <\/strong>$340 CAD<\/p><p>________________________________<\/p><h6>⛟ 7-Day No-Reason Return<br\/>⛟ 30-Day Refundable<br\/>🛠︎ 5-Year Warranty<\/h6><p><a href=\"https:\/\/benehike.com\/pages\/shipping-policy\" title=\"https:\/\/benehike.com\/pages\/shipping-policy\"><em><strong>MORE SHIPPING POLICY<\/strong><\/em><\/a><\/p>"
          }
        },
        "b9d44eac-6426-4093-a11d-b5d9446edb58": {
          "type": "question",
          "settings": {
            "title": "INSTALLATION",
            "answer": "<p><strong>Installation Instructions<\/strong><\/p><p><a href=\"https:\/\/cdn.shopify.com\/s\/files\/1\/0618\/8226\/9862\/files\/Ascendll_Aluminum_Shell_Side_Open_Rooftop_Tent_Manual_4f760c5b-73e5-4ee7-b996-8d4ce484d226.pdf?v=1689582169\" title=\"Ascendll V2 Aluminum Hard Shell Side Open Rooftop Tent  Installation Manual\"><em><strong>📩 Download the Manual<\/strong><\/em><\/a><\/p>"
          }
        }
      },
      "block_order": [
        "template--16416158613670__2ca79a2a-7dff-41ad-8c5f-cb2bb7070dc4-question-1",
        "template--16416158613670__2ca79a2a-7dff-41ad-8c5f-cb2bb7070dc4-question-2",
        "29d84539-711c-42d9-9d3d-77976e8ad492",
        "b9d44eac-6426-4093-a11d-b5d9446edb58"
      ],
      "settings": {
        "title": ""
      }
    },
    "4cd81335-7fa9-4aff-988c-306bf079bd62": {
      "type": "rich-text",
      "blocks": {
        "template--16416158613670__4cd81335-7fa9-4aff-988c-306bf079bd62-heading-1": {
          "type": "heading",
          "settings": {
            "title": "WHAT KINDS OF VEHICLES WOULD FIT IN RTT?",
            "use_h1": false
          }
        }
      },
      "block_order": [
        "template--16416158613670__4cd81335-7fa9-4aff-988c-306bf079bd62-heading-1"
      ],
      "settings": {
        "height": "small",
        "text_alignment": "center",
        "full_width": false,
        "color_scheme": "2"
      }
    },
    "830ff4a8-2410-4c34-a06e-420787822183": {
      "type": "scrolling-banner",
      "blocks": {
        "076820b5-9799-4402-ba56-b2359695174f": {
          "type": "image",
          "settings": {
            "image": "shopify:\/\/shop_images\/PICK-UP-TRUCK-q2fbvesih5dcwrzncgl165kgetq2fymkhrwn8vf270.png",
            "image_width": 200,
            "link": ""
          }
        },
        "template--16416158613670__830ff4a8-2410-4c34-a06e-420787822183-text-1": {
          "type": "text",
          "settings": {
            "text": "PICK UP TRUCK",
            "color": "rgba(0,0,0,0)",
            "link": "",
            "use_h1": false,
            "stencil_all_text": false,
            "stencil_text": ""
          }
        },
        "36e26c95-16dc-4a33-827d-74fc58a4c568": {
          "type": "image",
          "settings": {
            "image": "shopify:\/\/shop_images\/TRAILER-q2fbvfqcnzen8dya6yznqnbx07lfnnqatwk4q5do0s.png",
            "image_width": 200,
            "link": ""
          }
        },
        "0f652bea-0dee-428a-b5d7-7ed9177d7dd9": {
          "type": "text",
          "settings": {
            "text": "TRAILER",
            "color": "rgba(0,0,0,0)",
            "link": "",
            "use_h1": false,
            "stencil_all_text": false,
            "stencil_text": ""
          }
        },
        "558fd5ad-f718-46e9-9976-5c0e2f3213fd": {
          "type": "image",
          "settings": {
            "image": "shopify:\/\/shop_images\/FULL-SIZE-SUV-q2fbvduoabc2l610hy6elnsztfup89iu5n95rlggd8.png",
            "image_width": 200,
            "link": ""
          }
        },
        "9eec5214-b49d-4b98-9941-f15f4b6bf842": {
          "type": "text",
          "settings": {
            "text": "MID-SIZE SUV",
            "color": "rgba(0,0,0,0)",
            "link": "",
            "use_h1": false,
            "stencil_all_text": false,
            "stencil_text": ""
          }
        },
        "78552d19-f04f-4f65-a955-21837a8fd53a": {
          "type": "image",
          "settings": {
            "image": "shopify:\/\/shop_images\/FULL-SIZE-SUV-q2fbvduoabc2l610hy6elnsztfup89iu5n95rlggd8_71910132-52d4-4901-9ba2-902e4d1dda48.png",
            "image_width": 200,
            "link": ""
          }
        },
        "ee43fb84-df19-4dd4-a61b-8ebbcaf3b743": {
          "type": "text",
          "settings": {
            "text": "FULL-SIZE SUV",
            "color": "rgba(0,0,0,0)",
            "link": "",
            "use_h1": false,
            "stencil_all_text": false,
            "stencil_text": ""
          }
        },
        "bd6e6d07-5b93-4446-b5b3-1ac73bc11ef3": {
          "type": "image",
          "settings": {
            "image": "shopify:\/\/shop_images\/VAN-q2fbvgo6utfxjzwx1heab53dllgsvcu1617m7fc9uk.png",
            "image_width": 200,
            "link": ""
          }
        },
        "f989d211-1962-4c01-a9a5-0cd929462661": {
          "type": "text",
          "settings": {
            "text": "Van",
            "color": "rgba(0,0,0,0)",
            "link": "",
            "use_h1": false,
            "stencil_all_text": false,
            "stencil_text": ""
          }
        }
      },
      "block_order": [
        "076820b5-9799-4402-ba56-b2359695174f",
        "template--16416158613670__830ff4a8-2410-4c34-a06e-420787822183-text-1",
        "36e26c95-16dc-4a33-827d-74fc58a4c568",
        "0f652bea-0dee-428a-b5d7-7ed9177d7dd9",
        "558fd5ad-f718-46e9-9976-5c0e2f3213fd",
        "9eec5214-b49d-4b98-9941-f15f4b6bf842",
        "78552d19-f04f-4f65-a955-21837a8fd53a",
        "ee43fb84-df19-4dd4-a61b-8ebbcaf3b743",
        "bd6e6d07-5b93-4446-b5b3-1ac73bc11ef3",
        "f989d211-1962-4c01-a9a5-0cd929462661"
      ],
      "settings": {
        "full_width": true,
        "color_scheme": "2",
        "text_size": 20,
        "vertical_padding": 20,
        "speed": 20,
        "direction": "left",
        "font": "base",
        "space": 35
      }
    },
    "b4bcd257-6452-4fca-b928-571c9cdcd952": {
      "type": "key-features",
      "blocks": {
        "template--16416158613670__b4bcd257-6452-4fca-b928-571c9cdcd952-feature-2": {
          "type": "feature",
          "settings": {
            "image": "shopify:\/\/shop_images\/Ascendll_aluminum_side_open_rooftop_tent_view_3.jpg",
            "bg_color": "#f6f6f6",
            "bg_gradient": "",
            "text_color": "#171717",
            "heading": "EXPANDED ALUMINUM ALLOY SHELL",
            "text": "<ul><li>You don't have to worry about MPG, the 8-inch ultra-thin design reduces wind resistance and noise when driving.<\/li><li>Mothership-grade plating addresses the potential for rust, corrosion, and withstands harsh weather conditions and rough terrain.<\/li><li>Optional Crossbar Expansion: Bring bikes, kayaks, snowboards, or anything else you need for your next adventure.<\/li><\/ul>",
            "show_segments": true,
            "segments": 6,
            "active_segment": "1",
            "fill_segments": true,
            "show_labels": true,
            "label_left": "Additional",
            "label_middle": "",
            "label_right": "",
            "show_icon": true,
            "icon": "star"
          }
        },
        "template--16416158613670__b4bcd257-6452-4fca-b928-571c9cdcd952-feature-3": {
          "type": "feature",
          "settings": {
            "image": "shopify:\/\/shop_images\/Ascendll_V2_Aluminum_Shell_Rooftop_Tent_2_Person-_desc_04.jpg",
            "bg_color": "#f6f6f6",
            "bg_gradient": "",
            "text_color": "#505050",
            "heading": "VERSATILE CAPACITY",
            "text": "<p>The Ascendll features channel slots on all four sides, top, and bottom for versatile customization. Seamless integration of awning brackets provides quick access to awnings, canisters, tools, showers, and more.<\/p>",
            "show_segments": true,
            "segments": 6,
            "active_segment": "2",
            "fill_segments": true,
            "show_labels": true,
            "label_left": "Expand",
            "label_middle": "",
            "label_right": "",
            "show_icon": true,
            "icon": "star"
          }
        },
        "template--16416158613670__b4bcd257-6452-4fca-b928-571c9cdcd952-feature-1": {
          "type": "feature",
          "settings": {
            "image": "shopify:\/\/shop_images\/aluminum_pop_up_rooftop_tent_banner_13_fab5eab5-1daf-49dd-a21e-76bfee3fe952.jpg",
            "bg_color": "#f6f6f6",
            "bg_gradient": "",
            "text_color": "#171717",
            "heading": "FAMILY CAMPERS",
            "text": "<p>Luxurious California bed, big enough to sleep with furry. Also store a sleeping bag, quilt or blanket inside.<\/p>",
            "show_segments": true,
            "segments": 6,
            "active_segment": "3",
            "fill_segments": true,
            "show_labels": true,
            "label_left": "",
            "label_middle": "Size",
            "label_right": "",
            "show_icon": false,
            "icon": "star"
          }
        },
        "49014b63-7f0f-482e-aba1-9a239ec302f6": {
          "type": "feature",
          "settings": {
            "image": "shopify:\/\/shop_images\/aluminum_pop_up_rooftop_tent_22-transformed_07.jpg",
            "bg_color": "#e3e3e3",
            "bg_gradient": "",
            "text_color": "#505050",
            "heading": "FULL SIZE BED",
            "text": "<ul><li>Camping doesn't have to be tough. Sleep on luxury mattresses comparable to California kings.<\/li><li>A 2-inch high-density foam mattress allows you to sleep under the stars like a five-star hotel.<\/li><\/ul>",
            "show_segments": true,
            "segments": 6,
            "active_segment": "4",
            "fill_segments": true,
            "show_labels": true,
            "label_left": "",
            "label_middle": "Bed",
            "label_right": "",
            "show_icon": false,
            "icon": "star"
          }
        },
        "ef3fa946-e1b2-45e0-8577-d8d6da43ae9a": {
          "type": "feature",
          "settings": {
            "image": "shopify:\/\/shop_images\/Ascendll_aluminum_side_open_rooftop_tent_view_5.jpg",
            "bg_color": "#f6f6f6",
            "bg_gradient": "",
            "text_color": "#505050",
            "heading": "FASTEST SETUP",
            "text": "<ul><li>Opens in less than 60 seconds, which means you can enjoy more time relaxing and spending time with your family.<\/li><li>When closing the tent, you don't have to take the futon out to clean the contents, it stays inside.<\/li><\/ul>",
            "show_segments": true,
            "segments": 6,
            "active_segment": "5",
            "fill_segments": true,
            "show_labels": true,
            "label_left": "",
            "label_middle": "",
            "label_right": "Bright",
            "show_icon": false,
            "icon": "star"
          }
        },
        "bbb7f85c-9e87-427c-857d-334b327992f1": {
          "type": "feature",
          "settings": {
            "image": "shopify:\/\/shop_images\/Ascendll_aluminum_side_open_rooftop_tent_2224.jpg",
            "bg_color": "#f6f6f6",
            "bg_gradient": "",
            "text_color": "#505050",
            "heading": "INFINITE STORAGE",
            "text": "<p>The Vertical Storage Pockets On Both Sides Allow Easy Placement Of Small Items When Drowsiness Strikes.<\/p>",
            "show_segments": true,
            "segments": 6,
            "active_segment": "6",
            "fill_segments": true,
            "show_labels": true,
            "label_left": "",
            "label_middle": "",
            "label_right": "Storage",
            "show_icon": false,
            "icon": "star"
          }
        }
      },
      "block_order": [
        "template--16416158613670__b4bcd257-6452-4fca-b928-571c9cdcd952-feature-2",
        "template--16416158613670__b4bcd257-6452-4fca-b928-571c9cdcd952-feature-3",
        "template--16416158613670__b4bcd257-6452-4fca-b928-571c9cdcd952-feature-1",
        "49014b63-7f0f-482e-aba1-9a239ec302f6",
        "ef3fa946-e1b2-45e0-8577-d8d6da43ae9a",
        "bbb7f85c-9e87-427c-857d-334b327992f1"
      ],
      "settings": {
        "heading": "Key features",
        "image_max_width": 700,
        "media_aspect_ratio": "s",
        "image_position": "left",
        "segment_position": "over-text"
      }
    },
    "a7ef1531-0794-4cda-b3af-7936f0141206": {
      "type": "image-with-text",
      "blocks": {
        "template--16416158613670__a7ef1531-0794-4cda-b3af-7936f0141206-heading-1": {
          "type": "heading",
          "settings": {
            "title": "Stainless Steel Latch",
            "use_h1": false
          }
        },
        "template--16416158613670__a7ef1531-0794-4cda-b3af-7936f0141206-text-1": {
          "type": "text",
          "settings": {
            "text": "<p>Secure and convenient, the lockable latch on the rooftop tent provides added safety and ensures a stable and closed position.<\/p>",
            "enlarge_text": false
          }
        }
      },
      "block_order": [
        "template--16416158613670__a7ef1531-0794-4cda-b3af-7936f0141206-heading-1",
        "template--16416158613670__a7ef1531-0794-4cda-b3af-7936f0141206-text-1"
      ],
      "settings": {
        "image": "shopify:\/\/shop_images\/aluminum_pop_up_rooftop_tent_22-transformed_08_bd3e4844-1e91-45d7-8634-2fe268cfc8f3.jpg",
        "image_width": 700,
        "image_link": "",
        "image_position": "left",
        "text_alignment": "left",
        "color_scheme": "2"
      }
    },
    "129065a7-d3e1-4efd-9b20-314972590991": {
      "type": "image-with-text",
      "blocks": {
        "template--16416158613670__129065a7-d3e1-4efd-9b20-314972590991-heading-1": {
          "type": "heading",
          "settings": {
            "title": "Rainfly Pole Base",
            "use_h1": false
          }
        },
        "template--16416158613670__129065a7-d3e1-4efd-9b20-314972590991-text-1": {
          "type": "text",
          "settings": {
            "text": "<p>Durable and reinforced base, designed for safety and protection, preventing any risk of cuts or injuries to the hand.<\/p>",
            "enlarge_text": false
          }
        }
      },
      "block_order": [
        "template--16416158613670__129065a7-d3e1-4efd-9b20-314972590991-heading-1",
        "template--16416158613670__129065a7-d3e1-4efd-9b20-314972590991-text-1"
      ],
      "settings": {
        "image": "shopify:\/\/shop_images\/aluminum_pop_up_rooftop_tent_22-transformed_10.jpg",
        "image_width": 700,
        "image_link": "",
        "image_position": "right",
        "text_alignment": "left",
        "color_scheme": "2"
      }
    },
    "27b8c9cf-13ee-40db-afc9-e06096fb54e0": {
      "type": "image-with-text",
      "blocks": {
        "template--16416158613670__27b8c9cf-13ee-40db-afc9-e06096fb54e0-heading-1": {
          "type": "heading",
          "settings": {
            "title": "4 Season Protection",
            "use_h1": false
          }
        },
        "template--16416158613670__27b8c9cf-13ee-40db-afc9-e06096fb54e0-text-1": {
          "type": "text",
          "settings": {
            "text": "<ul><li>Rip-stop 600D Oxford with 280GSM cotton: PU 3000mm R<\/li><li>ating, UV50+, Can withstand harsh environmental conditions.<\/li><li>Whether you're backcountry camping or enjoying a day at the beach, our tent fabrics will give you the toughness you need to stay safe and dry.<\/li><\/ul>",
            "enlarge_text": false
          }
        }
      },
      "block_order": [
        "template--16416158613670__27b8c9cf-13ee-40db-afc9-e06096fb54e0-heading-1",
        "template--16416158613670__27b8c9cf-13ee-40db-afc9-e06096fb54e0-text-1"
      ],
      "settings": {
        "image": "shopify:\/\/shop_images\/aluminum_pop_up_rooftop_tent_banner_7.jpg",
        "image_width": 700,
        "image_link": "",
        "image_position": "left",
        "text_alignment": "left",
        "color_scheme": "1"
      }
    },
    "3d98a8f9-4460-463d-b870-e72073a9e37a": {
      "type": "image-with-text",
      "blocks": {
        "template--16416158613670__3d98a8f9-4460-463d-b870-e72073a9e37a-heading-1": {
          "type": "heading",
          "settings": {
            "title": "Excellent Insulation Structure",
            "use_h1": false
          }
        },
        "template--16416158613670__3d98a8f9-4460-463d-b870-e72073a9e37a-text-1": {
          "type": "text",
          "settings": {
            "text": "<p>Premier Insulated Aluminum Tube Frame Floor & Top Insulated Liner designed to help prevent condensation buildup and retain heat, ensuring your tent stays at the ideal temperature all night long.<\/p>",
            "enlarge_text": false
          }
        }
      },
      "block_order": [
        "template--16416158613670__3d98a8f9-4460-463d-b870-e72073a9e37a-heading-1",
        "template--16416158613670__3d98a8f9-4460-463d-b870-e72073a9e37a-text-1"
      ],
      "settings": {
        "image": "shopify:\/\/shop_images\/Ascendll_aluminum_side_open_rooftop_tent_view_6.jpg",
        "image_width": 700,
        "image_link": "",
        "image_position": "right",
        "text_alignment": "left",
        "color_scheme": "2"
      }
    },
    "d2ab2f52-25e2-41cc-b42d-3e5fe114eab9": {
      "type": "image-with-text",
      "blocks": {
        "template--16416158613670__d2ab2f52-25e2-41cc-b42d-3e5fe114eab9-heading-1": {
          "type": "heading",
          "settings": {
            "title": "Easy Installation",
            "use_h1": false
          }
        },
        "template--16416158613670__d2ab2f52-25e2-41cc-b42d-3e5fe114eab9-text-1": {
          "type": "text",
          "settings": {
            "text": "<p>Tighten 8 screws, kick back, and enjoy—no need for extra wrench or a headache!<\/p>",
            "enlarge_text": false
          }
        },
        "6f2da24e-2476-42a4-b277-88e30a03631f": {
          "type": "button",
          "settings": {
            "button_label": "View manual",
            "button_link": "https:\/\/cdn.shopify.com\/s\/files\/1\/0618\/8226\/9862\/files\/Ascendll_Aluminum_Shell_Side_Open_Rooftop_Tent_Manual_4f760c5b-73e5-4ee7-b996-8d4ce484d226.pdf?v=1689582169",
            "button_style": "primary"
          }
        }
      },
      "block_order": [
        "template--16416158613670__d2ab2f52-25e2-41cc-b42d-3e5fe114eab9-heading-1",
        "template--16416158613670__d2ab2f52-25e2-41cc-b42d-3e5fe114eab9-text-1",
        "6f2da24e-2476-42a4-b277-88e30a03631f"
      ],
      "settings": {
        "image": "shopify:\/\/shop_images\/Ascendll_V2_Aluminum_Shell_Rooftop_Tent_2_Person-_desc_010_H_9622e263-3480-429f-91f0-d0cf3b4c78b4.jpg",
        "image_width": 700,
        "image_link": "",
        "image_position": "left",
        "text_alignment": "left",
        "color_scheme": "2"
      }
    },
    "170245891781eeaafb": {
      "type": "apps",
      "blocks": {
        "b2c69e5c-d674-48b8-88cd-34b5fa0b20b2": {
          "type": "shopify:\/\/apps\/judge-me-reviews\/blocks\/review_widget\/61ccd3b1-a9f2-4160-9fe9-4fec8413e5d8",
          "settings": {
          }
        }
      },
      "block_order": [
        "b2c69e5c-d674-48b8-88cd-34b5fa0b20b2"
      ],
      "settings": {
        "full_width": false
      }
    },
    "related-products": {
      "type": "related-products",
      "settings": {
        "title": "You may also like",
        "show_vendor": false,
        "grid": 4
      }
    }
  },
  "order": [
    "main",
    "2ca79a2a-7dff-41ad-8c5f-cb2bb7070dc4",
    "4cd81335-7fa9-4aff-988c-306bf079bd62",
    "830ff4a8-2410-4c34-a06e-420787822183",
    "b4bcd257-6452-4fca-b928-571c9cdcd952",
    "a7ef1531-0794-4cda-b3af-7936f0141206",
    "129065a7-d3e1-4efd-9b20-314972590991",
    "27b8c9cf-13ee-40db-afc9-e06096fb54e0",
    "3d98a8f9-4460-463d-b870-e72073a9e37a",
    "d2ab2f52-25e2-41cc-b42d-3e5fe114eab9",
    "170245891781eeaafb",
    "related-products"
  ]
}
